eazzyformat/__init__.py
eazzyformat/parser.py
eazzyformat/string_iterators.py
eazzyformat-1.7.0.dist-info/LICENSE.txt
eazzyformat-1.7.0.dist-info/METADATA
eazzyformat-1.7.0.dist-info/WHEEL
eazzyformat-1.7.0.dist-info/RECORD
